http_message_signatures/__init__.py
http_message_signatures/_algorithms.py
http_message_signatures/algorithms.py
http_message_signatures/exceptions.py
http_message_signatures/py.typed
http_message_signatures/resolvers.py
http_message_signatures/signatures.py
http_message_signatures/structures.py
http_message_signatures/http_sfv/__init__.py
http_message_signatures/http_sfv/boolean.py
http_message_signatures/http_sfv/byteseq.py
http_message_signatures/http_sfv/date.py
http_message_signatures/http_sfv/decimal.py
http_message_signatures/http_sfv/dictionary.py
http_message_signatures/http_sfv/display_string.py
http_message_signatures/http_sfv/integer.py
http_message_signatures/http_sfv/item.py
http_message_signatures/http_sfv/list.py
http_message_signatures/http_sfv/string.py
http_message_signatures/http_sfv/token.py
http_message_signatures/http_sfv/types.py
http_message_signatures/http_sfv/util.py
http_message_signatures/http_sfv/util_json.py
http_message_signatures-2.0.1.dist-info/METADATA
http_message_signatures-2.0.1.dist-info/WHEEL
http_message_signatures-2.0.1.dist-info/licenses/LICENSE
http_message_signatures-2.0.1.dist-info/licenses/NOTICE
http_message_signatures-2.0.1.dist-info/RECORD
