Metadata-Version: 2.4
Name: http-message-signatures
Version: 2.0.1
Summary: An implementation of the IETF HTTP Message Signatures draft standard
Project-URL: Homepage, https://github.com/pyauth/http-message-signatures
Author: Andrey Kislyuk
Author-email: kislyuk@gmail.com
Maintainer: Andrey Kislyuk
Maintainer-email: kislyuk@gmail.com
License: Apache Software License
License-File: LICENSE
License-File: NOTICE
Classifier: Intended Audience :: Developers
Classifier: License :: OSI Approved :: Apache Software License
Classifier: Operating System :: MacOS :: MacOS X
Classifier: Operating System :: POSIX
Classifier: Programming Language :: Python
Classifier: Programming Language :: Python :: 3.10
Classifier: Programming Language :: Python :: 3.11
Classifier: Programming Language :: Python :: 3.12
Classifier: Programming Language :: Python :: 3.13
Classifier: Programming Language :: Python :: 3.14
Classifier: Topic :: Software Development :: Libraries :: Python Modules
Requires-Python: >=3.10
Requires-Dist: cryptography>=36.0.2
Provides-Extra: tests
Requires-Dist: build; extra == 'tests'
Requires-Dist: coverage; extra == 'tests'
Requires-Dist: flake8; extra == 'tests'
Requires-Dist: mypy; extra == 'tests'
Requires-Dist: requests; extra == 'tests'
Requires-Dist: ruff; extra == 'tests'
Requires-Dist: wheel; extra == 'tests'
